veritas_api/__init__.py
veritas_api/_base_client.py
veritas_api/_client.py
veritas_api/_compat.py
veritas_api/_constants.py
veritas_api/_exceptions.py
veritas_api/_files.py
veritas_api/_models.py
veritas_api/_qs.py
veritas_api/_resource.py
veritas_api/_response.py
veritas_api/_streaming.py
veritas_api/_types.py
veritas_api/_version.py
veritas_api/py.typed
veritas_api/_utils/__init__.py
veritas_api/_utils/_logs.py
veritas_api/_utils/_proxy.py
veritas_api/_utils/_reflection.py
veritas_api/_utils/_streams.py
veritas_api/_utils/_sync.py
veritas_api/_utils/_transform.py
veritas_api/_utils/_typing.py
veritas_api/_utils/_utils.py
veritas_api/lib/.keep
veritas_api/resources/__init__.py
veritas_api/resources/enrichments.py
veritas_api/resources/external_document_processing.py
veritas_api/types/__init__.py
veritas_api/types/enrichment_create_bulk_params.py
veritas_api/types/enrichment_create_bulk_response.py
veritas_api/types/enrichment_retrieve_response.py
veritas_api/types/external_document_processing_create_params.py
veritas_api/types/external_document_processing_create_response.py
veritas_api/types/external_document_processing_list_response.py
veritas_api/types/external_document_processing_retrieve_response.py
veritas_api-0.2.0.dist-info/METADATA
veritas_api-0.2.0.dist-info/WHEEL
veritas_api-0.2.0.dist-info/licenses/LICENSE
veritas_api-0.2.0.dist-info/RECORD
